README.rst
setup.py
cnfg/__init__.py
cnfg/cnfg.py
cnfg/test.py
cnfg.egg-info/PKG-INFO
cnfg.egg-info/SOURCES.txt
cnfg.egg-info/dependency_links.txt
cnfg.egg-info/top_level.txt