Metadata-Version: 1.1
Name: cnfg
Version: 1.0.0
Summary: simple Python config in your home directory
Home-page: https://github.com/ajschumacher/cnfg
Author: Aaron Schumacher
Author-email: ajschumacher@gmail.com
License: MIT
Download-URL: https://github.com/ajschumacher/cnfg/tarball/1.0.0
Platform: UNKNOWN
Classifier: Natural Language :: English
Classifier: Programming Language :: Python
Classifier: Programming Language :: Python :: 2.7
Classifier: Programming Language :: Python :: 3
Classifier: License :: OSI Approved :: MIT License
Classifier: Development Status :: 5 - Production/Stable
